{
  "id": "mug10",
  "asset_type": "FileBasedObject",
  "license": "None",
  "kwargs": {
    "render_filename": "{asset_dir}/mug10.blend",
    "render_import_kwargs": {
      "filepath": "models/mug10/mug10.blend/Object/mug",
      "directory": "models/mug10/mug10.blend/Object",
      "filename": "mug"
    }
  },
  "metadata": {
    "class_id": 6,
    "description": "Gray Mug",
    "xscale": 0.107,
    "yscale": 0.0824,
    "zscale": 0.076,
    "url": "https://sketchfab.com/3d-models/mug-cup-371febc7198f40179b9b84e60bfcf1ab",
    "type": "train"
  }
}